[
    {
        "id":"6084c",
        "email":"jasoncano0509@gmail.com",
        "phone":"1(555) 555-5555",
        "name":"Jason Cano",
        "hours":[0,1,1,4,10],
        "tutored":[
            {"date":1690887600000,"hours":1,"notes":""},
            {"date":1691082000000,"hours":2,"notes":""},
            {"date":1691082000000,"hours":2,"notes":""},
            {"date":1691331000000,"hours":1,"notes":""},
            {"date":1691420400000,"hours":1,"notes":""},
            {"date":1691506800000,"hours":3,"notes":""},
            {"date":1691596800000,"hours":3,"notes":""},
            {"date":1691686800000,"hours":2,"notes":""},
            {"date":1692032570010,"hours":1,"notes":""},

        ],
]